sun_stream/__init__.py
sun_stream-0.1.2.dist-info/LICENSE
sun_stream-0.1.2.dist-info/WHEEL
sun_stream-0.1.2.dist-info/METADATA
sun_stream-0.1.2.dist-info/RECORD
