Metadata-Version: 2.1
Name: sun-stream
Version: 0.1.2
Summary: Creating a stream of sun rises and sun sets, that only yields at the time of those events.
Home-page: https://github.com/PowerSnail/sun_stream
License: MIT
Author: PowerSnail
Author-email: hj@powersnail.com
Requires-Python: >=3.10,<4.0
Classifier: License :: OSI Approved :: MIT License
Classifier: Programming Language :: Python :: 3
Classifier: Programming Language :: Python :: 3.10
Classifier: Programming Language :: Python :: 3.11
Provides-Extra: docs
Requires-Dist: mkdocs (>=1.4.2,<2.0.0); extra == "docs"
Requires-Dist: mkdocstrings[python] (>=0.20.0,<0.21.0); extra == "docs"
Requires-Dist: requests (>=2,<3)
Project-URL: Documentation, https://sun-stream.readthedocs.io/en/latest/
Project-URL: Repository, https://github.com/PowerSnail/sun_stream
